webdriver_manager/__init__.py
webdriver_manager/chrome.py
webdriver_manager/firefox.py
webdriver_manager/microsoft.py
webdriver_manager/opera.py
webdriver_manager/py.typed
webdriver_manager/core/__init__.py
webdriver_manager/core/archive.py
webdriver_manager/core/config.py
webdriver_manager/core/constants.py
webdriver_manager/core/download_manager.py
webdriver_manager/core/driver.py
webdriver_manager/core/driver_cache.py
webdriver_manager/core/file_manager.py
webdriver_manager/core/http.py
webdriver_manager/core/logger.py
webdriver_manager/core/manager.py
webdriver_manager/core/os_manager.py
webdriver_manager/core/utils.py
webdriver_manager/drivers/__init__.py
webdriver_manager/drivers/chrome.py
webdriver_manager/drivers/edge.py
webdriver_manager/drivers/firefox.py
webdriver_manager/drivers/ie.py
webdriver_manager/drivers/opera.py
webdriver_manager-4.0.0.dist-info/LICENSE
webdriver_manager-4.0.0.dist-info/METADATA
webdriver_manager-4.0.0.dist-info/WHEEL
webdriver_manager-4.0.0.dist-info/top_level.txt
webdriver_manager-4.0.0.dist-info/RECORD
