Metadata-Version: 2.1
Name: webdriver-manager
Version: 4.0.0
Summary: Library provides the way to automatically manage drivers for different browsers
Home-page: https://github.com/SergeyPirogov/webdriver_manager
Author: Sergey Pirogov
Author-email: automationremarks@gmail.com
Keywords: testing,selenium,driver,test automation
Classifier: License :: OSI Approved :: Apache Software License
Classifier: Intended Audience :: Information Technology
Classifier: Intended Audience :: Developers
Classifier: Programming Language :: Python :: 3.7
Classifier: Programming Language :: Python :: 3.8
Classifier: Programming Language :: Python :: 3.9
Classifier: Programming Language :: Python :: 3.10
Classifier: Programming Language :: Python :: 3.11
Classifier: Topic :: Software Development :: Libraries :: Python Modules
Classifier: Operating System :: Microsoft :: Windows
Classifier: Operating System :: POSIX
Classifier: Operating System :: Unix
Classifier: Operating System :: MacOS
Requires-Python: >=3.7
License-File: LICENSE
